<?xml version="1.0" encoding="utf-8"?>
<ArrayOfTask xmlns:xsi="http://www.w3.org/2001/XMLSchema-instance" xmlns:xsd="http://www.w3.org/2001/XMLSchema">
  <Task>
    <ID>1</ID>
    <Nickname>Structural Analysis and Design</Nickname>
    <Description>Analyzing and designing structures for various projects.</Description>
    <Milestone>false</Milestone>
    <Created>2023-11-28T21:22:19.4406045+02:00</Created>
    <ProjectedStart>2024-05-25T21:22:19.394579+03:00</ProjectedStart>
    <ActualStart>2024-02-24T21:23:30.2372371+02:00</ActualStart>
    <Deadline xsi:nil="true" />
    <Duration>4</Duration>
    <ActualEnd>2024-02-24T21:26:27.9151507+02:00</ActualEnd>
    <AssignedEngineer xsi:nil="true" />
    <Difficulty>Intermediate</Difficulty>
    <Active>true</Active>
  </Task>
  <Task>
    <ID>2</ID>
    <Nickname>Systems Integration Testing</Nickname>
    <Description>Conducting testing to ensure seamless integration of systems.</Description>
    <Milestone>false</Milestone>
    <Created>2024-01-13T21:22:19.4524054+02:00</Created>
    <ProjectedStart>2024-12-19T21:22:19.394579+02:00</ProjectedStart>
    <ActualStart xsi:nil="true" />
    <Deadline xsi:nil="true" />
    <Duration>33</Duration>
    <ActualEnd xsi:nil="true" />
    <AssignedEngineer xsi:nil="true" />
    <Difficulty>Beginner</Difficulty>
    <Active>true</Active>
  </Task>
  <Task>
    <ID>3</ID>
    <Nickname>Finite Element Analysis (FEA)</Nickname>
    <Description>Performing Finite Element Analysis for structural simulations.</Description>
    <Milestone>false</Milestone>
    <Created>2023-12-12T21:22:19.4617406+02:00</Created>
    <ProjectedStart>2025-02-24T21:22:19.394579+02:00</ProjectedStart>
    <ActualStart xsi:nil="true" />
    <Deadline xsi:nil="true" />
    <Duration>97</Duration>
    <ActualEnd xsi:nil="true" />
    <AssignedEngineer xsi:nil="true" />
    <Difficulty>Advanced</Difficulty>
    <Active>true</Active>
  </Task>
  <Task>
    <ID>4</ID>
    <Nickname>Prototyping and Validation</Nickname>
    <Description>Creating prototypes and validating their functionality.</Description>
    <Milestone>false</Milestone>
    <Created>2023-12-21T21:22:19.4646174+02:00</Created>
    <ProjectedStart>2024-08-09T21:22:19.394579+03:00</ProjectedStart>
    <ActualStart xsi:nil="true" />
    <Deadline xsi:nil="true" />
    <Duration>97</Duration>
    <ActualEnd xsi:nil="true" />
    <AssignedEngineer xsi:nil="true" />
    <Difficulty>Expert</Difficulty>
    <Active>true</Active>
  </Task>
  <Task>
    <ID>5</ID>
    <Nickname>Project Scheduling and Planning</Nickname>
    <Description>Planning and scheduling tasks for successful project completion.</Description>
    <Milestone>false</Milestone>
    <Created>2024-02-16T21:22:19.4679708+02:00</Created>
    <ProjectedStart>2025-01-21T21:22:19.394579+02:00</ProjectedStart>
    <ActualStart xsi:nil="true" />
    <Deadline xsi:nil="true" />
    <Duration>36</Duration>
    <ActualEnd xsi:nil="true" />
    <AssignedEngineer xsi:nil="true" />
    <Difficulty>Advanced</Difficulty>
    <Active>true</Active>
  </Task>
  <Task>
    <ID>6</ID>
    <Nickname>Environmental Impact Assessment</Nickname>
    <Description>Assessing and mitigating environmental impacts of engineering projects.</Description>
    <Milestone>false</Milestone>
    <Created>2024-01-18T21:22:19.4709573+02:00</Created>
    <ProjectedStart>2024-12-04T21:22:19.394579+02:00</ProjectedStart>
    <ActualStart xsi:nil="true" />
    <Deadline xsi:nil="true" />
    <Duration>15</Duration>
    <ActualEnd xsi:nil="true" />
    <AssignedEngineer xsi:nil="true" />
    <Difficulty>Beginner</Difficulty>
    <Active>true</Active>
  </Task>
  <Task>
    <ID>7</ID>
    <Nickname>Design Optimization</Nickname>
    <Description>Optimizing designs for efficiency and performance.</Description>
    <Milestone>false</Milestone>
    <Created>2023-11-27T21:22:19.4743641+02:00</Created>
    <ProjectedStart>2024-02-24T21:22:19.394579+02:00</ProjectedStart>
    <ActualStart>2024-02-24T21:23:26.2372371+02:00</ActualStart>
    <Deadline xsi:nil="true" />
    <Duration>91</Duration>
    <ActualEnd>2024-02-24T21:23:28.2372371+02:00</ActualEnd>
    <AssignedEngineer xsi:nil="true" />
    <Difficulty>Advanced</Difficulty>
    <Active>true</Active>
  </Task>
  <Task>
    <ID>8</ID>
    <Nickname>Materials Selection and Testing</Nickname>
    <Description>Selecting materials and conducting testing for suitability.</Description>
    <Milestone>false</Milestone>
    <Created>2024-01-31T21:22:19.4773858+02:00</Created>
    <ProjectedStart>2024-08-04T21:22:19.394579+03:00</ProjectedStart>
    <ActualStart xsi:nil="true" />
    <Deadline xsi:nil="true" />
    <Duration>5</Duration>
    <ActualEnd xsi:nil="true" />
    <AssignedEngineer xsi:nil="true" />
    <Difficulty>Beginner</Difficulty>
    <Active>true</Active>
  </Task>
  <Task>
    <ID>9</ID>
    <Nickname>Quality Assurance and Control</Nickname>
    <Description>Ensuring and controlling the quality of engineering processes.</Description>
    <Milestone>false</Milestone>
    <Created>2023-11-29T21:22:19.4806066+02:00</Created>
    <ProjectedStart>2024-05-29T21:22:19.394579+03:00</ProjectedStart>
    <ActualStart>2024-02-24T21:26:32.9151507+02:00</ActualStart>
    <Deadline xsi:nil="true" />
    <Duration>45</Duration>
    <ActualEnd>2024-02-24T21:26:40.9151507+02:00</ActualEnd>
    <AssignedEngineer xsi:nil="true" />
    <Difficulty>Expert</Difficulty>
    <Active>true</Active>
  </Task>
  <Task>
    <ID>10</ID>
    <Nickname>Regulatory Compliance Review</Nickname>
    <Description>Reviewing and ensuring compliance with regulatory standards.</Description>
    <Milestone>false</Milestone>
    <Created>2024-02-03T21:22:19.4837804+02:00</Created>
    <ProjectedStart>2025-02-10T21:22:19.394579+02:00</ProjectedStart>
    <ActualStart xsi:nil="true" />
    <Deadline xsi:nil="true" />
    <Duration>14</Duration>
    <ActualEnd xsi:nil="true" />
    <AssignedEngineer xsi:nil="true" />
    <Difficulty>Expert</Difficulty>
    <Active>true</Active>
  </Task>
  <Task>
    <ID>11</ID>
    <Nickname>Cost Estimation and Budgeting</Nickname>
    <Description>Estimating project costs and creating budgets.</Description>
    <Milestone>false</Milestone>
    <Created>2024-02-10T21:22:19.4866072+02:00</Created>
    <ProjectedStart>2024-09-23T21:22:19.394579+03:00</ProjectedStart>
    <ActualStart xsi:nil="true" />
    <Deadline xsi:nil="true" />
    <Duration>72</Duration>
    <ActualEnd xsi:nil="true" />
    <AssignedEngineer xsi:nil="true" />
    <Difficulty>AdvancedBeginner</Difficulty>
    <Active>true</Active>
  </Task>
  <Task>
    <ID>12</ID>
    <Nickname>Geotechnical Investigation</Nickname>
    <Description>Investigating soil and rock properties for construction projects.</Description>
    <Milestone>false</Milestone>
    <Created>2023-11-19T21:22:19.4898179+02:00</Created>
    <ProjectedStart>2024-05-29T21:22:19.394579+03:00</ProjectedStart>
    <ActualStart>2024-02-24T21:26:42.9151507+02:00</ActualStart>
    <Deadline xsi:nil="true" />
    <Duration>31</Duration>
    <ActualEnd xsi:nil="true" />
    <AssignedEngineer>394550188</AssignedEngineer>
    <Difficulty>Advanced</Difficulty>
    <Active>true</Active>
  </Task>
  <Task>
    <ID>13</ID>
    <Nickname>Risk Assessment and Management</Nickname>
    <Description>Assessing and managing risks associated with engineering projects.</Description>
    <Milestone>false</Milestone>
    <Created>2024-02-14T21:22:19.4928815+02:00</Created>
    <ProjectedStart>2024-08-09T21:22:19.394579+03:00</ProjectedStart>
    <ActualStart xsi:nil="true" />
    <Deadline xsi:nil="true" />
    <Duration>1</Duration>
    <ActualEnd xsi:nil="true" />
    <AssignedEngineer xsi:nil="true" />
    <Difficulty>AdvancedBeginner</Difficulty>
    <Active>true</Active>
  </Task>
  <Task>
    <ID>14</ID>
    <Nickname>3D Modeling and Rendering</Nickname>
    <Description>Creating detailed 3D models and realistic renderings.</Description>
    <Milestone>false</Milestone>
    <Created>2023-11-23T21:22:19.496202+02:00</Created>
    <ProjectedStart>2024-02-24T21:22:19.394579+02:00</ProjectedStart>
    <ActualStart>2024-02-24T21:22:30.394579+02:00</ActualStart>
    <Deadline xsi:nil="true" />
    <Duration>96</Duration>
    <ActualEnd>2024-02-24T21:23:18.2372371+02:00</ActualEnd>
    <AssignedEngineer xsi:nil="true" />
    <Difficulty>Beginner</Difficulty>
    <Active>true</Active>
  </Task>
  <Task>
    <ID>15</ID>
    <Nickname>Failure Mode and Effect Analysis (FMEA)</Nickname>
    <Description>Analyzing potential failure modes and their effects.</Description>
    <Milestone>false</Milestone>
    <Created>2024-01-23T21:22:19.4996555+02:00</Created>
    <ProjectedStart>2024-08-10T21:22:19.394579+03:00</ProjectedStart>
    <ActualStart xsi:nil="true" />
    <Deadline xsi:nil="true" />
    <Duration>44</Duration>
    <ActualEnd xsi:nil="true" />
    <AssignedEngineer xsi:nil="true" />
    <Difficulty>Expert</Difficulty>
    <Active>true</Active>
  </Task>
  <Task>
    <ID>16</ID>
    <Nickname>Field Inspection and Monitoring</Nickname>
    <Description>Inspecting and monitoring projects in the field.</Description>
    <Milestone>false</Milestone>
    <Created>2024-02-11T21:22:19.5030715+02:00</Created>
    <ProjectedStart>2025-01-05T21:22:19.394579+02:00</ProjectedStart>
    <ActualStart xsi:nil="true" />
    <Deadline xsi:nil="true" />
    <Duration>15</Duration>
    <ActualEnd xsi:nil="true" />
    <AssignedEngineer xsi:nil="true" />
    <Difficulty>Expert</Difficulty>
    <Active>true</Active>
  </Task>
  <Task>
    <ID>17</ID>
    <Nickname>Energy Efficiency Analysis</Nickname>
    <Description>Analyzing and improving energy efficiency in designs.</Description>
    <Milestone>false</Milestone>
    <Created>2024-01-28T21:22:19.5071726+02:00</Created>
    <ProjectedStart>2024-06-29T21:22:19.394579+03:00</ProjectedStart>
    <ActualStart xsi:nil="true" />
    <Deadline xsi:nil="true" />
    <Duration>36</Duration>
    <ActualEnd xsi:nil="true" />
    <AssignedEngineer xsi:nil="true" />
    <Difficulty>AdvancedBeginner</Difficulty>
    <Active>true</Active>
  </Task>
  <Task>
    <ID>18</ID>
    <Nickname>Simulation and Modeling</Nickname>
    <Description>Conducting simulations and mathematical modeling.</Description>
    <Milestone>false</Milestone>
    <Created>2024-01-27T21:22:19.5106821+02:00</Created>
    <ProjectedStart>2025-01-20T21:22:19.394579+02:00</ProjectedStart>
    <ActualStart xsi:nil="true" />
    <Deadline xsi:nil="true" />
    <Duration>21</Duration>
    <ActualEnd xsi:nil="true" />
    <AssignedEngineer xsi:nil="true" />
    <Difficulty>Expert</Difficulty>
    <Active>true</Active>
  </Task>
  <Task>
    <ID>19</ID>
    <Nickname>Technical Documentation and Reporting</Nickname>
    <Description>Preparing technical documentation and reports.</Description>
    <Milestone>false</Milestone>
    <Created>2023-12-04T21:22:19.5142587+02:00</Created>
    <ProjectedStart>2024-12-19T21:22:19.394579+02:00</ProjectedStart>
    <ActualStart xsi:nil="true" />
    <Deadline xsi:nil="true" />
    <Duration>53</Duration>
    <ActualEnd xsi:nil="true" />
    <AssignedEngineer xsi:nil="true" />
    <Difficulty>AdvancedBeginner</Difficulty>
    <Active>true</Active>
  </Task>
  <Task>
    <ID>20</ID>
    <Nickname>Supplier and Vendor Coordination</Nickname>
    <Description>Coordinating with suppliers and vendors for project components.</Description>
    <Milestone>false</Milestone>
    <Created>2023-11-30T21:22:19.5180166+02:00</Created>
    <ProjectedStart>2024-12-19T21:22:19.394579+02:00</ProjectedStart>
    <ActualStart xsi:nil="true" />
    <Deadline xsi:nil="true" />
    <Duration>17</Duration>
    <ActualEnd xsi:nil="true" />
    <AssignedEngineer xsi:nil="true" />
    <Difficulty>Beginner</Difficulty>
    <Active>true</Active>
  </Task>
</ArrayOfTask>